{
   "agent": "AutobahnPython/0.10.9",
   "behavior": "OK",
   "behaviorClose": "OK",
   "case": 44,
   "closedByMe": false,
   "createStats": true,
   "createWirelog": true,
   "description": "Send small text message, then send frame with reserved control <b>Opcode = 15</b> and non-empty payload, then send Ping.",
   "droppedByMe": false,
   "duration": 2,
   "expectation": "Echo for first message is received, but then connection is failed immediately, since reserved opcode frame is used. A Pong is not received.",
   "expected": {
      "NON-STRICT": [],
      "OK": [
         [
            "message",
            "Hello, world!",
            false
         ]
      ]
   },
   "expectedClose": {
      "closeCode": [
         1002
      ],
      "closedByMe": false,
      "requireClean": false
   },
   "failedByMe": false,
   "httpRequest": "GET / HTTP/1.1\r\nUser-Agent: AutobahnTestSuite/0.8.1-0.10.9\r\nHost: 127.0.0.1:9001\r\nUpgrade: WebSocket\r\nConnection: Upgrade\r\nPragma: no-cache\r\nCache-Control: no-cache\r\nSec-WebSocket-Key: 1ph1HEv4nnYuzWql2nwf/Q==\r\nSec-WebSocket-Version: 13\r\n\r\n",
   "httpResponse": "HTTP/1.1 101 Switching Protocols\r\nServer: AutobahnPython/0.10.9\r\nX-Powered-By: AutobahnPython/0.10.9\r\nUpgrade: WebSocket\r\nConnection: Upgrade\r\nSec-WebSocket-Accept: mHZxMGfTwEY1so+F/v3TNHuZZME=\r\n\r\n",
   "id": "4.2.5",
   "isServer": false,
   "localCloseCode": null,
   "localCloseReason": null,
   "received": [
      [
         "message",
         "Hello, world!",
         false
      ]
   ],
   "remoteCloseCode": null,
   "remoteCloseReason": null,
   "reportCompressionRatio": false,
   "reportTime": false,
   "result": "Actual events match at least one expected.",
   "resultClose": "Connection was properly closed",
   "rxFrameStats": {
      "1": 1
   },
   "rxOctetStats": {
      "15": 1,
      "197": 1
   },
   "started": "2021-07-17T23:53:16.344Z",
   "trafficStats": null,
   "txFrameStats": {
      "1": 1,
      "9": 1,
      "15": 1
   },
   "txOctetStats": {
      "1": 22,
      "240": 1
   },
   "wasClean": false,
   "wasCloseHandshakeTimeout": false,
   "wasNotCleanReason": "peer dropped the TCP connection without previous WebSocket closing handshake",
   "wasOpenHandshakeTimeout": false,
   "wasServerConnectionDropTimeout": false,
   "wirelog": [
      [
         "TO",
         [
            240,
            "474554202f20485454502f312e310d0a557365722d4167656e743a204175746f6261686e5465737453756974652f302e382e312d302e31302e390d0a486f7374 ..."
         ],
         false
      ],
      [
         "RO",
         [
            197,
            "485454502f312e312031303120537769746368696e672050726f746f636f6c730d0a5365727665723a204175746f6261686e507974686f6e2f302e31302e390d ..."
         ]
      ],
      [
         "TF",
         [
            13,
            "Hello, world!"
         ],
         1,
         true,
         0,
         "da58edbd",
         null,
         1,
         false
      ],
      [
         "TO",
         [
            1,
            "81"
         ],
         true
      ],
      [
         "TF",
         [
            13,
            "Hello, world!"
         ],
         15,
         true,
         0,
         "da51e32f",
         null,
         1,
         false
      ],
      [
         "TF",
         [
            0,
            ""
         ],
         9,
         true,
         0,
         "492d1e83",
         null,
         1,
         false
      ],
      [
         "KL",
         1
      ],
      [
         "TO",
         [
            1,
            "8d"
         ],
         true
      ],
      [
         "TO",
         [
            1,
            "da"
         ],
         true
      ],
      [
         "TO",
         [
            1,
            "58"
         ],
         true
      ],
      [
         "TO",
         [
            1,
            "ed"
         ],
         true
      ],
      [
         "TO",
         [
            1,
            "bd"
         ],
         true
      ],
      [
         "TO",
         [
            1,
            "92"
         ],
         true
      ],
      [
         "TO",
         [
            1,
            "3d"
         ],
         true
      ],
      [
         "TO",
         [
            1,
            "81"
         ],
         true
      ],
      [
         "TO",
         [
            1,
            "d1"
         ],
         true
      ],
      [
         "TO",
         [
            1,
            "b5"
         ],
         true
      ],
      [
         "TO",
         [
            1,
            "74"
         ],
         true
      ],
      [
         "TO",
         [
            1,
            "cd"
         ],
         true
      ],
      [
         "TO",
         [
            1,
            "ca"
         ],
         true
      ],
      [
         "TO",
         [
            1,
            "b5"
         ],
         true
      ],
      [
         "TO",
         [
            1,
            "2a"
         ],
         true
      ],
      [
         "TO",
         [
            1,
            "81"
         ],
         true
      ],
      [
         "TO",
         [
            1,
            "d9"
         ],
         true
      ],
      [
         "TO",
         [
            1,
            "fb"
         ],
         true
      ],
      [
         "TO",
         [
            1,
            "8f"
         ],
         true
      ],
      [
         "TO",
         [
            1,
            "8d"
         ],
         true
      ],
      [
         "TO",
         [
            1,
            "da"
         ],
         true
      ],
      [
         "RO",
         [
            15,
            "810d48656c6c6f2c20776f726c6421"
         ]
      ],
      [
         "RF",
         [
            13,
            "Hello, world!"
         ],
         1,
         true,
         0,
         false,
         null
      ]
   ]
}