{
   "agent": "wsServer",
   "behavior": "OK",
   "behaviorClose": "OK",
   "case": 61,
   "closedByMe": false,
   "createStats": true,
   "createWirelog": true,
   "description": "Repeated 2x: Continuation Frame with FIN = true (where there is nothing to continue), then text Message fragmented into 2 fragments.",
   "droppedByMe": false,
   "duration": 0,
   "expectation": "The connection is failed immediately, since there is no message to continue.",
   "expected": {
      "OK": []
   },
   "expectedClose": {
      "closeCode": [
         1002
      ],
      "closedByMe": false,
      "requireClean": false
   },
   "failedByMe": false,
   "httpRequest": "GET / HTTP/1.1\r\nUser-Agent: AutobahnTestSuite/0.8.1-0.10.9\r\nHost: 127.0.0.1:8080\r\nUpgrade: WebSocket\r\nConnection: Upgrade\r\nPragma: no-cache\r\nCache-Control: no-cache\r\nSec-WebSocket-Key: 0r333f45k41RhpM2FaaR3A==\r\nSec-WebSocket-Version: 13\r\n\r\n",
   "httpResponse": "HTTP/1.1 101 Switching Protocols\r\nUpgrade: websocket\r\nConnection: Upgrade\r\nSec-WebSocket-Accept: 22OH7T0U+cFlFei5ZVJlGR54c3Q=\r\n\r\n",
   "id": "5.17",
   "isServer": false,
   "localCloseCode": null,
   "localCloseReason": null,
   "received": [],
   "remoteCloseCode": null,
   "remoteCloseReason": null,
   "reportCompressionRatio": false,
   "reportTime": false,
   "result": "Actual events match at least one expected.",
   "resultClose": "Connection was properly closed",
   "rxFrameStats": {},
   "rxOctetStats": {
      "129": 1
   },
   "started": "2020-11-19T20:36:04.770Z",
   "trafficStats": null,
   "txFrameStats": {
      "0": 4,
      "1": 2
   },
   "txOctetStats": {
      "15": 6,
      "240": 1
   },
   "wasClean": false,
   "wasCloseHandshakeTimeout": false,
   "wasNotCleanReason": "peer dropped the TCP connection without previous WebSocket closing handshake",
   "wasOpenHandshakeTimeout": false,
   "wasServerConnectionDropTimeout": false,
   "wirelog": [
      [
         "TO",
         [
            240,
            "474554202f20485454502f312e310d0a557365722d4167656e743a204175746f6261686e5465737453756974652f302e382e312d302e31302e390d0a486f7374 ..."
         ],
         false
      ],
      [
         "RO",
         [
            129,
            "485454502f312e312031303120537769746368696e672050726f746f636f6c730d0a557067726164653a20776562736f636b65740d0a436f6e6e656374696f6e ..."
         ]
      ],
      [
         "TF",
         [
            9,
            "fragment1"
         ],
         0,
         true,
         0,
         "89b97aee",
         null,
         null,
         false
      ],
      [
         "TO",
         [
            15,
            "808989b97aeeefcb1b89e4dc149ab8"
         ],
         false
      ],
      [
         "TF",
         [
            9,
            "fragment2"
         ],
         1,
         false,
         0,
         "8261cddc",
         null,
         null,
         false
      ],
      [
         "TO",
         [
            15,
            "01898261cddce413acbbef04a3a8b0"
         ],
         false
      ],
      [
         "TF",
         [
            9,
            "fragment3"
         ],
         0,
         true,
         0,
         "5c309dc8",
         null,
         null,
         false
      ],
      [
         "TO",
         [
            15,
            "80895c309dc83a42fcaf3155f3bc6f"
         ],
         false
      ],
      [
         "TF",
         [
            9,
            "fragment1"
         ],
         0,
         true,
         0,
         "51c77dad",
         null,
         null,
         false
      ],
      [
         "TO",
         [
            15,
            "808951c77dad37b51cca3ca213d960"
         ],
         false
      ],
      [
         "TF",
         [
            9,
            "fragment2"
         ],
         1,
         false,
         0,
         "49ca9671",
         null,
         null,
         false
      ],
      [
         "TO",
         [
            15,
            "018949ca96712fb8f71624aff8057b"
         ],
         false
      ],
      [
         "TF",
         [
            9,
            "fragment3"
         ],
         0,
         true,
         0,
         "ad2565fc",
         null,
         null,
         false
      ],
      [
         "TO",
         [
            15,
            "8089ad2565fccb57049bc0400b889e"
         ],
         false
      ],
      [
         "KL",
         1
      ]
   ]
}